i4srcm/__init__.py
i4srcm/async_client.py
i4srcm/client.py
i4srcm/ctl.py
i4srcm/fs_client.py
i4srcm/lxmlutil.py
i4srcm/main.py
i4srcm/selwhere.py
i4srcm/system_config.py
i4srcm/workflow_preset.py
i4srcm/xml/DBPath.py
i4srcm/xml/XmlBinaryStream.py
i4srcm/xml/__init__.py
pyrcmclient-0.0.13.dist-info/LICENSE.txt
pyrcmclient-0.0.13.dist-info/METADATA
pyrcmclient-0.0.13.dist-info/WHEEL
pyrcmclient-0.0.13.dist-info/entry_points.txt
pyrcmclient-0.0.13.dist-info/top_level.txt
pyrcmclient-0.0.13.dist-info/RECORD
