Metadata-Version: 2.1
Name: pyrcmclient
Version: 0.0.13
Summary: python client for i4s-rcm
Home-page: https://github.com/quatre-i-science/pyrcmclient
Author: quatre-i-science
Author-email: i4s_eng@i4s.co.jp
License: MIT
Keywords: i4s rcm client
Classifier: Programming Language :: Python :: 3.11
Classifier: Programming Language :: Python :: 3.12
License-File: LICENSE.txt
Requires-Dist: requests>=2.32.3
Requires-Dist: aiohttp>=3.11.10
Requires-Dist: lxml>=5.3.0
Requires-Dist: types-lxml>=2024.9.16
Requires-Dist: paramiko>=3.5.0
Requires-Dist: pandas>=2.2.3
